{"bill":{"bill_id":853031,"change_hash":"04c278b7cc4fefd31b183be68d09f363","session_id":1120,"session":{"session_id":1120,"state_id":5,"year_start":2015,"year_end":2016,"prefile":0,"sine_die":1,"prior":1,"special":0,"session_tag":"Regular Session","session_title":"2015-2016 Regular Session","session_name":"2015-2016 Session"},"url":"https:\/\/legiscan.com\/CA\/bill\/AB2523\/2015","state_link":"http:\/\/www.leginfo.ca.gov\/cgi-bin\/postquery?bill_number=ab_2523&sess=1516&house=A","completed":0,"status":2,"status_date":"2016-06-02","progress":[{"date":"2016-02-19","event":1},{"date":"2016-03-17","event":10},{"date":"2016-03-17","event":9},{"date":"2016-03-28","event":9},{"date":"2016-04-06","event":10},{"date":"2016-04-07","event":9},{"date":"2016-04-18","event":10},{"date":"2016-04-20","event":9},{"date":"2016-05-04","event":9},{"date":"2016-05-27","event":10},{"date":"2016-06-02","event":2},{"date":"2016-06-06","event":9},{"date":"2016-06-09","event":9},{"date":"2016-06-14","event":10},{"date":"2016-06-14","event":9},{"date":"2016-06-22","event":10},{"date":"2016-06-22","event":9},{"date":"2016-08-01","event":10},{"date":"2016-08-01","event":9},{"date":"2016-08-11","event":10}],"state":"CA","state_id":5,"bill_number":"AB2523","bill_type":"B","bill_type_id":"1","body":"A","body_id":19,"current_body":"S","current_body_id":20,"title":"Local elective offices: contribution limitations.","description":"An act to amend and repeal Sections 35177 and 72029 of the Education Code, to amend and repeal Sections 10003, 10202, and 10544 of the Elections Code, and to amend Section 85301 of, to amend, repeal, and add Sections 85305, 85306, 85307, 85315, 85316, 85317, and 85318 of, and to add Section 85702.5 to, the Government Code, relating to elections.","pending_committee_id":0,"committee":[],"referrals":[{"date":"2016-03-17","committee_id":453,"chamber":"A","chamber_id":19,"name":"Elections and Redistricting"},{"date":"2016-04-18","committee_id":449,"chamber":"A","chamber_id":19,"name":"Appropriations"},{"date":"2016-06-06","committee_id":489,"chamber":"S","chamber_id":20,"name":"Rules"},{"date":"2016-06-09","committee_id":1796,"chamber":"S","chamber_id":20,"name":"Elections and Constitutional Amendments"},{"date":"2016-06-22","committee_id":475,"chamber":"S","chamber_id":20,"name":"Appropriations"}],"history":[{"date":"2016-02-19","action":"Introduced. To print. ","chamber":"A","chamber_id":19,"importance":1},{"date":"2016-02-21","action":"From printer. May be heard in committee March 22.","chamber":"A","chamber_id":19,"importance":0},{"date":"2016-02-22","action":"Read first time.","chamber":"A","chamber_id":19,"importance":0},{"date":"2016-03-17","action":"Referred to Com. on E. & R. From committee chair, with author's amendments: Amend, and re-refer to Com. on E. & R. Read second time and amended.","chamber":"A","chamber_id":19,"importance":1},{"date":"2016-03-28","action":"Re-referred to Com. on E. & R.","chamber":"A","chamber_id":19,"importance":1},{"date":"2016-04-06","action":"From committee chair, with author's amendments: Amend, and re-refer to Com. on E. & R. Read second time and amended.","chamber":"A","chamber_id":19,"importance":1},{"date":"2016-04-07","action":"Re-referred to Com. on E. & R.","chamber":"A","chamber_id":19,"importance":1},{"date":"2016-04-18","action":"From committee: Amend, and do pass as amended and re-refer to Com. on APPR. (Ayes 5. Noes 2.) (April 13).","chamber":"A","chamber_id":19,"importance":1},{"date":"2016-04-19","action":"Read second time and amended.","chamber":"A","chamber_id":19,"importance":0},{"date":"2016-04-20","action":"Re-referred to Com. on APPR.","chamber":"A","chamber_id":19,"importance":1},{"date":"2016-05-04","action":"In committee: Set, first hearing. Referred to APPR. suspense file.","chamber":"A","chamber_id":19,"importance":1},{"date":"2016-05-27","action":"From committee: Amend, and do pass as amended. (Ayes 14. Noes 5.) (May 27).","chamber":"A","chamber_id":19,"importance":1},{"date":"2016-05-31","action":"Read second time and amended. Ordered returned to second reading.","chamber":"A","chamber_id":19,"importance":0},{"date":"2016-06-01","action":"Read second time. Ordered to third reading.","chamber":"A","chamber_id":19,"importance":0},{"date":"2016-06-02","action":"Read third time. Passed. Ordered to the Senate. (Ayes 51. Noes 26. Page 5195.)","chamber":"A","chamber_id":19,"importance":1},{"date":"2016-06-06","action":"In Senate. Read first time. To Com. on RLS. for assignment.","chamber":"S","chamber_id":20,"importance":1},{"date":"2016-06-09","action":"Referred to Com. on E. & C.A.","chamber":"S","chamber_id":20,"importance":1},{"date":"2016-06-14","action":"From committee chair, with author's amendments: Amend, and re-refer to committee. Read second time, amended, and re-referred to Com. on E. & C.A.","chamber":"S","chamber_id":20,"importance":1},{"date":"2016-06-22","action":"From committee: Do pass and re-refer to Com. on APPR. (Ayes 4. Noes 1.) (June 21). Re-referred to Com. on APPR.","chamber":"S","chamber_id":20,"importance":1},{"date":"2016-08-01","action":"From committee chair, with author's amendments: Amend, and re-refer to committee. Read second time, amended, and re-referred to Com. on APPR. In committee: Referred to APPR. suspense file.","chamber":"S","chamber_id":20,"importance":1},{"date":"2016-08-11","action":"From committee: Amend, and do pass as amended. (Ayes 5. Noes 2.) (August 11).","chamber":"S","chamber_id":20,"importance":1},{"date":"2016-08-15","action":"Read second time and amended. Ordered to third reading.","chamber":"S","chamber_id":20,"importance":0},{"date":"2016-08-29","action":"Read third time. Refused passage. (Ayes 25. Noes 14. Page 5495.). Motion to reconsider made by Senator Allen. Reconsideration granted. (Ayes 39. Noes 0. Page 5495.)","chamber":"S","chamber_id":20,"importance":0},{"date":"2016-08-31","action":"Ordered to inactive file at the request of Senator Allen.","chamber":"S","chamber_id":20,"importance":0},{"date":"2016-11-30","action":"Died on Senate inactive file.","chamber":"S","chamber_id":20,"importance":0}],"sponsors":[{"people_id":14115,"person_hash":"7fp7wtje","party_id":"1","state_id":5,"party":"D","role_id":1,"role":"Rep","name":"Kevin Mullin","first_name":"Kevin","middle_name":"","last_name":"Mullin","suffix":"","nickname":"","district":"HD-022","ftm_eid":13008543,"votesmart_id":105586,"opensecrets_id":"","knowwho_pid":390304,"ballotpedia":"Kevin_Mullin_(California)","sponsor_type_id":1,"sponsor_order":1,"committee_sponsor":0,"committee_id":0,"state_federal":0},{"people_id":16033,"person_hash":"rso35jci","party_id":"1","state_id":5,"party":"D","role_id":1,"role":"Rep","name":"Lorena Gonzalez Fletcher","first_name":"Lorena","middle_name":"","last_name":"Gonzalez Fletcher","suffix":"","nickname":"","district":"HD-080","ftm_eid":133178,"votesmart_id":144488,"opensecrets_id":"","knowwho_pid":460820,"ballotpedia":"Lorena_Gonzalez_Fletcher","sponsor_type_id":2,"sponsor_order":2,"committee_sponsor":0,"committee_id":0,"state_federal":0}],"sasts":[],"subjects":[],"texts":[{"doc_id":1345840,"date":"2016-02-19","type":"Introduced","type_id":1,"mime":"text\/html","mime_id":1,"url":"https:\/\/legiscan.com\/CA\/text\/AB2523\/id\/1345840","state_link":"http:\/\/www.leginfo.ca.gov\/pub\/15-16\/bill\/asm\/ab_2501-2550\/ab_2523_bill_20160219_introduced.html","text_size":1719,"text_hash":"aecef7b55061a5450477aa0949b38b14"},{"doc_id":1371898,"date":"2016-03-17","type":"Amended","type_id":3,"mime":"text\/html","mime_id":1,"url":"https:\/\/legiscan.com\/CA\/text\/AB2523\/id\/1371898","state_link":"http:\/\/www.leginfo.ca.gov\/pub\/15-16\/bill\/asm\/ab_2501-2550\/ab_2523_bill_20160317_amended_asm_v98.html","text_size":9462,"text_hash":"93ea02a995fc42eeb63c9393378c2b9f"},{"doc_id":1385037,"date":"2016-04-06","type":"Amended","type_id":3,"mime":"text\/html","mime_id":1,"url":"https:\/\/legiscan.com\/CA\/text\/AB2523\/id\/1385037","state_link":"http:\/\/www.leginfo.ca.gov\/pub\/15-16\/bill\/asm\/ab_2501-2550\/ab_2523_bill_20160406_amended_asm_v97.html","text_size":10514,"text_hash":"23dfebe8c63a28284513f098e57d75bd"},{"doc_id":1393282,"date":"2016-04-19","type":"Amended","type_id":3,"mime":"text\/html","mime_id":1,"url":"https:\/\/legiscan.com\/CA\/text\/AB2523\/id\/1393282","state_link":"http:\/\/www.leginfo.ca.gov\/pub\/15-16\/bill\/asm\/ab_2501-2550\/ab_2523_bill_20160419_amended_asm_v96.html","text_size":11698,"text_hash":"4315bc4a8ba46084587fa2eeac20df15"},{"doc_id":1414063,"date":"2016-05-31","type":"Amended","type_id":3,"mime":"text\/html","mime_id":1,"url":"https:\/\/legiscan.com\/CA\/text\/AB2523\/id\/1414063","state_link":"http:\/\/www.leginfo.ca.gov\/pub\/15-16\/bill\/asm\/ab_2501-2550\/ab_2523_bill_20160531_amended_asm_v95.html","text_size":14471,"text_hash":"72981336d7b83df6d010605202a816f9"},{"doc_id":1418683,"date":"2016-06-14","type":"Amended","type_id":3,"mime":"text\/html","mime_id":1,"url":"https:\/\/legiscan.com\/CA\/text\/AB2523\/id\/1418683","state_link":"http:\/\/www.leginfo.ca.gov\/pub\/15-16\/bill\/asm\/ab_2501-2550\/ab_2523_bill_20160614_amended_sen_v94.html","text_size":17009,"text_hash":"7da7a60ec726667ed30c9d664a8dd052"},{"doc_id":1424210,"date":"2016-08-01","type":"Amended","type_id":3,"mime":"text\/html","mime_id":1,"url":"https:\/\/legiscan.com\/CA\/text\/AB2523\/id\/1424210","state_link":"http:\/\/www.leginfo.ca.gov\/pub\/15-16\/bill\/asm\/ab_2501-2550\/ab_2523_bill_20160801_amended_sen_v93.html","text_size":34379,"text_hash":"453352138086ee6a43c5451570a205e3"},{"doc_id":1425192,"date":"2016-08-15","type":"Amended","type_id":3,"mime":"text\/html","mime_id":1,"url":"https:\/\/legiscan.com\/CA\/text\/AB2523\/id\/1425192","state_link":"http:\/\/www.leginfo.ca.gov\/pub\/15-16\/bill\/asm\/ab_2501-2550\/ab_2523_bill_20160815_amended_sen_v92.html","text_size":30651,"text_hash":"24e00756ef730fc6035ca7674f448c04"}],"votes":[{"roll_call_id":532538,"date":"2016-04-13","desc":"Do pass as amended and be re-referred to the Committee on \tAppropriations","yea":5,"nay":2,"nv":0,"absent":0,"total":7,"passed":1,"chamber":"A","chamber_id":19,"url":"https:\/\/legiscan.com\/CA\/rollcall\/AB2523\/id\/532538","state_link":"http:\/\/www.leginfo.ca.gov\/pub\/15-16\/bill\/asm\/ab_2501-2550\/ab_2523_vote_20160413_000001_asm_comm.html"},{"roll_call_id":549251,"date":"2016-05-27","desc":"Do pass as amended","yea":14,"nay":5,"nv":0,"absent":1,"total":20,"passed":1,"chamber":"A","chamber_id":19,"url":"https:\/\/legiscan.com\/CA\/rollcall\/AB2523\/id\/549251","state_link":"http:\/\/www.leginfo.ca.gov\/pub\/15-16\/bill\/asm\/ab_2501-2550\/ab_2523_vote_20160527_000001_asm_comm.html"},{"roll_call_id":550976,"date":"2016-06-02","desc":"AB 2523 MULLIN  Assembly Third Reading","yea":51,"nay":26,"nv":0,"absent":3,"total":80,"passed":1,"chamber":"A","chamber_id":19,"url":"https:\/\/legiscan.com\/CA\/rollcall\/AB2523\/id\/550976","state_link":"http:\/\/www.leginfo.ca.gov\/pub\/15-16\/bill\/asm\/ab_2501-2550\/ab_2523_vote_20160602_0122PM_asm_floor.html"},{"roll_call_id":554817,"date":"2016-06-21","desc":"Do pass, but re-refer to the Committee on Appropriations","yea":4,"nay":1,"nv":0,"absent":0,"total":5,"passed":1,"chamber":"S","chamber_id":20,"url":"https:\/\/legiscan.com\/CA\/rollcall\/AB2523\/id\/554817","state_link":"http:\/\/www.leginfo.ca.gov\/pub\/15-16\/bill\/asm\/ab_2501-2550\/ab_2523_vote_20160621_000001_sen_comm.html"},{"roll_call_id":558816,"date":"2016-08-01","desc":"Placed on Appropriations Suspense file","yea":7,"nay":0,"nv":0,"absent":0,"total":7,"passed":1,"chamber":"S","chamber_id":20,"url":"https:\/\/legiscan.com\/CA\/rollcall\/AB2523\/id\/558816","state_link":"http:\/\/www.leginfo.ca.gov\/pub\/15-16\/bill\/asm\/ab_2501-2550\/ab_2523_vote_20160801_000001_sen_comm.html"},{"roll_call_id":559554,"date":"2016-08-11","desc":"Do pass as amended","yea":5,"nay":2,"nv":0,"absent":0,"total":7,"passed":1,"chamber":"S","chamber_id":20,"url":"https:\/\/legiscan.com\/CA\/rollcall\/AB2523\/id\/559554","state_link":"http:\/\/www.leginfo.ca.gov\/pub\/15-16\/bill\/asm\/ab_2501-2550\/ab_2523_vote_20160811_000001_sen_comm.html"},{"roll_call_id":561415,"date":"2016-08-29","desc":"Assembly 3rd Reading AB2523 Mullin By Allen","yea":25,"nay":14,"nv":0,"absent":0,"total":39,"passed":0,"chamber":"S","chamber_id":20,"url":"https:\/\/legiscan.com\/CA\/rollcall\/AB2523\/id\/561415","state_link":"http:\/\/www.leginfo.ca.gov\/pub\/15-16\/bill\/asm\/ab_2501-2550\/ab_2523_vote_20160829_0506PM_sen_floor.html"},{"roll_call_id":561416,"date":"2016-08-29","desc":"Assembly 3rd Reading AB2523 Mullin By Allen","yea":39,"nay":0,"nv":0,"absent":0,"total":39,"passed":1,"chamber":"S","chamber_id":20,"url":"https:\/\/legiscan.com\/CA\/rollcall\/AB2523\/id\/561416","state_link":"http:\/\/www.leginfo.ca.gov\/pub\/15-16\/bill\/asm\/ab_2501-2550\/ab_2523_vote_20160829_0507PM_sen_floor.html"}],"amendments":[],"supplements":[],"calendar":[{"type_id":1,"type":"Hearing","date":"2016-04-13","time":"09:00","location":"","description":"Assembly Elections And Redistricting Hearing"},{"type_id":1,"type":"Hearing","date":"2016-04-13","time":"09:00","location":"State Capitol, Room 444","description":"Assembly Elections And Redistricting Hearing"},{"type_id":1,"type":"Hearing","date":"2016-06-21","time":"13:30","location":"Room 3191","description":"Senate Elections and Constitutional Amendments Hearing"},{"type_id":1,"type":"Hearing","date":"2016-08-01","time":"10:00","location":"John L. Burton Hearing Room","description":"Senate Appropriations Hearing"},{"type_id":1,"type":"Hearing","date":"2016-08-11","time":"00:00","location":"John L. Burton Hearing Room","description":"Senate Appropriations Hearing"}]}}