{"bill":{"bill_id":577487,"change_hash":"b40b3edd493645fc6da8ceb46df6ee14","session_id":993,"session":{"session_id":993,"state_id":5,"year_start":2013,"year_end":2014,"prefile":0,"sine_die":1,"prior":1,"special":0,"session_tag":"Regular Session","session_title":"2013-2014 Regular Session","session_name":"2013-2014 Session"},"url":"https:\/\/legiscan.com\/CA\/bill\/AB1432\/2013","state_link":"http:\/\/www.leginfo.ca.gov\/cgi-bin\/postquery?bill_number=ab_1432&sess=1314&house=A","completed":1,"status":4,"status_date":"2014-09-29","progress":[{"date":"2014-01-06","event":1},{"date":"2014-01-17","event":9},{"date":"2014-02-11","event":10},{"date":"2014-02-12","event":9},{"date":"2014-03-27","event":10},{"date":"2014-03-27","event":9},{"date":"2014-05-06","event":10},{"date":"2014-05-08","event":9},{"date":"2014-05-14","event":9},{"date":"2014-05-23","event":10},{"date":"2014-05-28","event":2},{"date":"2014-05-28","event":9},{"date":"2014-06-05","event":9},{"date":"2014-06-18","event":10},{"date":"2014-06-18","event":9},{"date":"2014-06-25","event":10},{"date":"2014-06-25","event":9},{"date":"2014-08-04","event":10},{"date":"2014-08-04","event":9},{"date":"2014-08-14","event":10},{"date":"2014-08-22","event":3},{"date":"2014-09-29","event":8},{"date":"2014-09-29","event":4}],"state":"CA","state_id":5,"bill_number":"AB1432","bill_type":"B","bill_type_id":"1","body":"A","body_id":19,"current_body":"A","current_body_id":19,"title":"Mandated child abuse reporting: school employees: training.","description":"An act to repeal Section 44690 of, and to repeal and add Section 44691 of, the Education Code, and to amend Section 11165.7 of the Penal Code, relating to child abuse reporting.","pending_committee_id":0,"committee":[],"referrals":[{"date":"2014-01-17","committee_id":455,"chamber":"A","chamber_id":19,"name":"Education"},{"date":"2014-03-27","committee_id":468,"chamber":"A","chamber_id":19,"name":"Public Safety"},{"date":"2014-05-06","committee_id":449,"chamber":"A","chamber_id":19,"name":"Appropriations"},{"date":"2014-05-28","committee_id":489,"chamber":"S","chamber_id":20,"name":"Rules"},{"date":"2014-06-05","committee_id":477,"chamber":"S","chamber_id":20,"name":"Education"},{"date":"2014-06-18","committee_id":487,"chamber":"S","chamber_id":20,"name":"Public Safety"},{"date":"2014-06-25","committee_id":475,"chamber":"S","chamber_id":20,"name":"Appropriations"}],"history":[{"date":"2014-01-06","action":"Read first time. To print. ","chamber":"A","chamber_id":19,"importance":1},{"date":"2014-01-07","action":"From printer. May be heard in committee February 6.","chamber":"A","chamber_id":19,"importance":0},{"date":"2014-01-17","action":"Referred to Coms. on ED. and PUB. S.","chamber":"A","chamber_id":19,"importance":1},{"date":"2014-02-11","action":"From committee chair, with author's amendments: Amend, and re-refer to Com. on ED. Read second time and amended.","chamber":"A","chamber_id":19,"importance":1},{"date":"2014-02-12","action":"Re-referred to Com. on ED.","chamber":"A","chamber_id":19,"importance":1},{"date":"2014-03-27","action":"From committee: Do pass and re-refer to Com. on PUB. S. (Ayes 5. Noes 0.) (March 26). Re-referred to Com. on PUB. S.","chamber":"A","chamber_id":19,"importance":1},{"date":"2014-05-06","action":"From committee: Do pass as amended and re-refer to Com. on APPR. (Ayes 5. Noes 0.) (April 29).","chamber":"A","chamber_id":19,"importance":1},{"date":"2014-05-07","action":"Read second time and amended.","chamber":"A","chamber_id":19,"importance":0},{"date":"2014-05-08","action":"Re-referred to Com. on APPR.","chamber":"A","chamber_id":19,"importance":1},{"date":"2014-05-14","action":"In committee: Set, first hearing. Referred to APPR. suspense file.","chamber":"A","chamber_id":19,"importance":1},{"date":"2014-05-23","action":"From committee: Do pass as amended. (Ayes 13. Noes 1.) . Read second time and amended. Ordered to second reading.","chamber":"A","chamber_id":19,"importance":1},{"date":"2014-05-27","action":"Read second time. Ordered to third reading.","chamber":"A","chamber_id":19,"importance":0},{"date":"2014-05-28","action":"Read third time. Passed. Ordered to the Senate. (Ayes 66. Noes 5. Page 5232.)","chamber":"A","chamber_id":19,"importance":1},{"date":"2014-05-28","action":"In Senate. Read first time. To Com. on RLS. for assignment.","chamber":"S","chamber_id":20,"importance":1},{"date":"2014-06-05","action":"Referred to Coms. on ED. and PUB. S.","chamber":"S","chamber_id":20,"importance":1},{"date":"2014-06-18","action":"From committee: Do pass and re-refer to Com. on PUB. S. (Ayes 7. Noes 0.) (June 18). Re-referred to Com. on PUB. S.","chamber":"S","chamber_id":20,"importance":1},{"date":"2014-06-25","action":"From committee: Do pass and re-refer to Com. on APPR. (Ayes 5. Noes 2.) (June 24). Re-referred to Com. on APPR.","chamber":"S","chamber_id":20,"importance":1},{"date":"2014-08-04","action":"From committee chair, with author's amendments: Amend, and re-refer to committee. Read second time, amended, and re-referred to Com. on APPR. In committee: Placed on APPR. suspense file.","chamber":"S","chamber_id":20,"importance":1},{"date":"2014-08-14","action":"From committee: Do pass. (Ayes 5. Noes 0.) (August 14).","chamber":"S","chamber_id":20,"importance":1},{"date":"2014-08-18","action":"Read second time. Ordered to third reading.","chamber":"S","chamber_id":20,"importance":0},{"date":"2014-08-20","action":"Read third time. Passed. Ordered to the Assembly. (Ayes 31. Noes 3. Page 4654.).","chamber":"S","chamber_id":20,"importance":0},{"date":"2014-08-20","action":"In Assembly. Concurrence in Senate amendments pending. May be considered on or after August 22 pursuant to Assembly Rule 77.","chamber":"A","chamber_id":19,"importance":0},{"date":"2014-08-22","action":"Senate amendments concurred in. To Engrossing and Enrolling. (Ayes 61. Noes 13. Page 6319.).","chamber":"A","chamber_id":19,"importance":1},{"date":"2014-09-05","action":"Enrolled and presented to the Governor at 3:30 p.m.","chamber":"A","chamber_id":19,"importance":0},{"date":"2014-09-29","action":"Approved by the Governor.","chamber":"","chamber_id":0,"importance":0},{"date":"2014-09-29","action":"Chaptered by Secretary of State - Chapter 797, Statutes of 2014.","chamber":"","chamber_id":0,"importance":1}],"sponsors":[{"people_id":9547,"person_hash":"xkdz8ekq","party_id":"1","state_id":5,"party":"D","role_id":1,"role":"Rep","name":"Mike Gatto","first_name":"Mike","middle_name":"","last_name":"Gatto","suffix":"","nickname":"","district":"HD-043","ftm_eid":767512,"votesmart_id":120220,"opensecrets_id":"","knowwho_pid":215724,"ballotpedia":"Mike_Gatto","sponsor_type_id":1,"sponsor_order":1,"committee_sponsor":0,"committee_id":0,"state_federal":0},{"people_id":10960,"person_hash":"izncxh1c","party_id":"1","state_id":5,"party":"D","role_id":1,"role":"Rep","name":"Susan Bonilla","first_name":"Susan","middle_name":"A.","last_name":"Bonilla","suffix":"","nickname":"","district":"HD-014","ftm_eid":299294,"votesmart_id":82208,"opensecrets_id":"","knowwho_pid":290920,"ballotpedia":"Susan_Bonilla","sponsor_type_id":1,"sponsor_order":2,"committee_sponsor":0,"committee_id":0,"state_federal":0},{"people_id":11610,"person_hash":"uo9ka10g","party_id":"1","state_id":5,"party":"D","role_id":1,"role":"Rep","name":"Nora Campos","first_name":"Nora","middle_name":"","last_name":"Campos","suffix":"","nickname":"","district":"HD-027","ftm_eid":196260,"votesmart_id":70451,"opensecrets_id":"","knowwho_pid":290931,"ballotpedia":"Nora_Campos","sponsor_type_id":2,"sponsor_order":3,"committee_sponsor":0,"committee_id":0,"state_federal":0},{"people_id":16094,"person_hash":"m68q8yjl","party_id":"1","state_id":5,"party":"D","role_id":1,"role":"Rep","name":"Matt Dababneh","first_name":"Matt","middle_name":"","last_name":"Dababneh","suffix":"","nickname":"","district":"HD-045","ftm_eid":18912256,"votesmart_id":144893,"opensecrets_id":"","knowwho_pid":242136,"ballotpedia":"Matt_Dababneh","sponsor_type_id":2,"sponsor_order":4,"committee_sponsor":0,"committee_id":0,"state_federal":0},{"people_id":10963,"person_hash":"9hcbn4sm","party_id":"1","state_id":5,"party":"D","role_id":1,"role":"Rep","name":"Roger Dickinson","first_name":"Roger","middle_name":"","last_name":"Dickinson","suffix":"","nickname":"","district":"HD-007","ftm_eid":13008457,"votesmart_id":28560,"opensecrets_id":"","knowwho_pid":290913,"ballotpedia":"Roger_Dickinson","sponsor_type_id":2,"sponsor_order":5,"committee_sponsor":0,"committee_id":0,"state_federal":0},{"people_id":11921,"person_hash":"l4r2vx0r","party_id":"2","state_id":5,"party":"R","role_id":2,"role":"Sen","name":"Anthony Cannella","first_name":"Anthony","middle_name":"","last_name":"Cannella","suffix":"","nickname":"","district":"SD-012","ftm_eid":13011175,"votesmart_id":70467,"opensecrets_id":"","knowwho_pid":289332,"ballotpedia":"Anthony_Cannella","sponsor_type_id":3,"sponsor_order":6,"committee_sponsor":0,"committee_id":0,"state_federal":0}],"sasts":[],"subjects":[],"texts":[{"doc_id":905747,"date":"2014-01-06","type":"Introduced","type_id":1,"mime":"text\/html","mime_id":1,"url":"https:\/\/legiscan.com\/CA\/text\/AB1432\/id\/905747","state_link":"http:\/\/www.leginfo.ca.gov\/pub\/13-14\/bill\/asm\/ab_1401-1450\/ab_1432_bill_20140106_introduced.html","text_size":3579,"text_hash":"62e1b5c260e290e3040d69a52b3a22e4"},{"doc_id":956330,"date":"2014-02-11","type":"Amended","type_id":3,"mime":"text\/html","mime_id":1,"url":"https:\/\/legiscan.com\/CA\/text\/AB1432\/id\/956330","state_link":"http:\/\/www.leginfo.ca.gov\/pub\/13-14\/bill\/asm\/ab_1401-1450\/ab_1432_bill_20140211_amended_asm_v98.html","text_size":21681,"text_hash":"7af0f78af4bcca808024204396745196"},{"doc_id":1020348,"date":"2014-05-07","type":"Amended","type_id":3,"mime":"text\/html","mime_id":1,"url":"https:\/\/legiscan.com\/CA\/text\/AB1432\/id\/1020348","state_link":"http:\/\/www.leginfo.ca.gov\/pub\/13-14\/bill\/asm\/ab_1401-1450\/ab_1432_bill_20140507_amended_asm_v97.html","text_size":19578,"text_hash":"84aee7b5d9ad682ac3172ec85fccd37d"},{"doc_id":1027781,"date":"2014-05-23","type":"Amended","type_id":3,"mime":"text\/html","mime_id":1,"url":"https:\/\/legiscan.com\/CA\/text\/AB1432\/id\/1027781","state_link":"http:\/\/www.leginfo.ca.gov\/pub\/13-14\/bill\/asm\/ab_1401-1450\/ab_1432_bill_20140523_amended_asm_v96.html","text_size":19540,"text_hash":"b5856c4eb2543b45b04198fa19847413"},{"doc_id":1041338,"date":"2014-08-04","type":"Amended","type_id":3,"mime":"text\/html","mime_id":1,"url":"https:\/\/legiscan.com\/CA\/text\/AB1432\/id\/1041338","state_link":"http:\/\/www.leginfo.ca.gov\/pub\/13-14\/bill\/asm\/ab_1401-1450\/ab_1432_bill_20140804_amended_sen_v95.html","text_size":19436,"text_hash":"7011c88aa214a0cfe53425f115ea6e74"},{"doc_id":1043848,"date":"2014-08-26","type":"Enrolled","type_id":5,"mime":"text\/html","mime_id":1,"url":"https:\/\/legiscan.com\/CA\/text\/AB1432\/id\/1043848","state_link":"http:\/\/www.leginfo.ca.gov\/pub\/13-14\/bill\/asm\/ab_1401-1450\/ab_1432_bill_20140826_enrolled.html","text_size":18792,"text_hash":"335899867c8e0f82baeef31ddd97e3a2"},{"doc_id":1047246,"date":"2014-09-29","type":"Chaptered","type_id":6,"mime":"text\/html","mime_id":1,"url":"https:\/\/legiscan.com\/CA\/text\/AB1432\/id\/1047246","state_link":"http:\/\/www.leginfo.ca.gov\/pub\/13-14\/bill\/asm\/ab_1401-1450\/ab_1432_bill_20140929_chaptered.html","text_size":18900,"text_hash":"3c61072712802317139f71a1c9af0ce7"}],"votes":[{"roll_call_id":348161,"date":"2014-03-26","desc":"Do pass and be re-referred to the Committee on Public Safety","yea":5,"nay":0,"nv":0,"absent":2,"total":7,"passed":1,"chamber":"A","chamber_id":19,"url":"https:\/\/legiscan.com\/CA\/rollcall\/AB1432\/id\/348161","state_link":"http:\/\/www.leginfo.ca.gov\/pub\/13-14\/bill\/asm\/ab_1401-1450\/ab_1432_vote_20140326_000002_asm_comm.html"},{"roll_call_id":360459,"date":"2014-04-29","desc":"Do pass as amended and be re-referred to the Committee on \tAppropriations","yea":5,"nay":0,"nv":0,"absent":2,"total":7,"passed":1,"chamber":"A","chamber_id":19,"url":"https:\/\/legiscan.com\/CA\/rollcall\/AB1432\/id\/360459","state_link":"http:\/\/www.leginfo.ca.gov\/pub\/13-14\/bill\/asm\/ab_1401-1450\/ab_1432_vote_20140429_000001_asm_comm.html"},{"roll_call_id":366789,"date":"2014-05-23","desc":"Do pass as amended","yea":13,"nay":1,"nv":0,"absent":3,"total":17,"passed":1,"chamber":"A","chamber_id":19,"url":"https:\/\/legiscan.com\/CA\/rollcall\/AB1432\/id\/366789","state_link":"http:\/\/www.leginfo.ca.gov\/pub\/13-14\/bill\/asm\/ab_1401-1450\/ab_1432_vote_20140523_000002_asm_comm.html"},{"roll_call_id":368143,"date":"2014-05-28","desc":"AB 1432 GATTO  Assembly Third Reading","yea":66,"nay":5,"nv":0,"absent":8,"total":79,"passed":1,"chamber":"A","chamber_id":19,"url":"https:\/\/legiscan.com\/CA\/rollcall\/AB1432\/id\/368143","state_link":"http:\/\/www.leginfo.ca.gov\/pub\/13-14\/bill\/asm\/ab_1401-1450\/ab_1432_vote_20140528_1123AM_asm_floor.html"},{"roll_call_id":372711,"date":"2014-06-18","desc":"Do pass, but re-refer to the Committee on Public Safety","yea":7,"nay":0,"nv":0,"absent":0,"total":7,"passed":1,"chamber":"S","chamber_id":20,"url":"https:\/\/legiscan.com\/CA\/rollcall\/AB1432\/id\/372711","state_link":"http:\/\/www.leginfo.ca.gov\/pub\/13-14\/bill\/asm\/ab_1401-1450\/ab_1432_vote_20140618_000001_sen_comm.html"},{"roll_call_id":374424,"date":"2014-06-24","desc":"Do pass, but re-refer to the Committee on Appropriations","yea":5,"nay":2,"nv":0,"absent":0,"total":7,"passed":1,"chamber":"S","chamber_id":20,"url":"https:\/\/legiscan.com\/CA\/rollcall\/AB1432\/id\/374424","state_link":"http:\/\/www.leginfo.ca.gov\/pub\/13-14\/bill\/asm\/ab_1401-1450\/ab_1432_vote_20140624_000001_sen_comm.html"},{"roll_call_id":376506,"date":"2014-08-04","desc":"Placed on Appropriations Suspense file","yea":7,"nay":0,"nv":0,"absent":0,"total":7,"passed":1,"chamber":"S","chamber_id":20,"url":"https:\/\/legiscan.com\/CA\/rollcall\/AB1432\/id\/376506","state_link":"http:\/\/www.leginfo.ca.gov\/pub\/13-14\/bill\/asm\/ab_1401-1450\/ab_1432_vote_20140804_000002_sen_comm.html"},{"roll_call_id":377300,"date":"2014-08-14","desc":"Do pass","yea":5,"nay":0,"nv":2,"absent":0,"total":7,"passed":1,"chamber":"S","chamber_id":20,"url":"https:\/\/legiscan.com\/CA\/rollcall\/AB1432\/id\/377300","state_link":"http:\/\/www.leginfo.ca.gov\/pub\/13-14\/bill\/asm\/ab_1401-1450\/ab_1432_vote_20140814_000003_sen_comm.html"},{"roll_call_id":377900,"date":"2014-08-20","desc":"Assembly 3rd Reading AB1432 Gatto By DeSaulnier","yea":31,"nay":3,"nv":6,"absent":0,"total":40,"passed":1,"chamber":"S","chamber_id":20,"url":"https:\/\/legiscan.com\/CA\/rollcall\/AB1432\/id\/377900","state_link":"http:\/\/www.leginfo.ca.gov\/pub\/13-14\/bill\/asm\/ab_1401-1450\/ab_1432_vote_20140820_1245PM_sen_floor.html"},{"roll_call_id":378209,"date":"2014-08-22","desc":"AB 1432 GATTO  Concurrence in Senate Amendments","yea":61,"nay":13,"nv":0,"absent":5,"total":79,"passed":1,"chamber":"A","chamber_id":19,"url":"https:\/\/legiscan.com\/CA\/rollcall\/AB1432\/id\/378209","state_link":"http:\/\/www.leginfo.ca.gov\/pub\/13-14\/bill\/asm\/ab_1401-1450\/ab_1432_vote_20140822_1017AM_asm_floor.html"}],"amendments":[],"supplements":[],"calendar":[]}}